sentry_strip_sensitive_data/__init__.py
sentry_strip_sensitive_data/before_send_func_generator.py
sentry_strip_sensitive_data-0.0.2.dist-info/LICENSE
sentry_strip_sensitive_data-0.0.2.dist-info/METADATA
sentry_strip_sensitive_data-0.0.2.dist-info/WHEEL
sentry_strip_sensitive_data-0.0.2.dist-info/top_level.txt
sentry_strip_sensitive_data-0.0.2.dist-info/RECORD
