Metadata-Version: 2.1
Name: sentry-strip-sensitive-data
Version: 0.0.2
Summary: sentry strip sensitive data
Home-page: https://github.com/go-nambu/sentry-strip-sensitive-data.git
Author: Go Nambu
Maintainer: Go Nambu
License: MIT
Download-URL: https://github.com/go-nambu/sentry-strip-sensitive-data.git
Platform: UNKNOWN
Classifier: Programming Language :: Python :: 3
Classifier: Programming Language :: Python :: 3.8
Classifier: Programming Language :: Python :: 3 :: Only
Requires-Python: >=3.6
